graph_tensor/__init__.py
graph_tensor/graph/__init__.py
graph_tensor/graph/atom.py
graph_tensor/graph/creator.py
graph_tensor/graph/param.py
graph_tensor/graph/test.py
graph_tensor/graph/window.py
graph_tensor/tools/__init__.py
graph_tensor/tools/tool_tip.py
graph_tensor-0.1.0.dist-info/LICENSE
graph_tensor-0.1.0.dist-info/METADATA
graph_tensor-0.1.0.dist-info/WHEEL
graph_tensor-0.1.0.dist-info/top_level.txt
graph_tensor-0.1.0.dist-info/RECORD
